terminal-colours/__init__.py
terminal-colours/colours.py
terminal_colours/__init__.py
terminal_colours/colours.py
terminal_colours-0.4.dist-info/DESCRIPTION.rst
terminal_colours-0.4.dist-info/METADATA
terminal_colours-0.4.dist-info/RECORD
terminal_colours-0.4.dist-info/WHEEL
terminal_colours-0.4.dist-info/metadata.json
terminal_colours-0.4.dist-info/top_level.txt
