Metadata-Version: 2.0
Name: terminal-colours
Version: 0.4
Summary: A simple package to allow the use of colours when outputting to the terminal
Home-page: https://github.com/g-farrow/terminal_colours
Author: Greg Farrow
Author-email: greg.farrow1@gmail.com
License: MIT
Keywords: terminal output colours colors color colour print format formatting
Platform: UNKNOWN
Classifier: Programming Language :: Python :: 3
Classifier: Programming Language :: Python :: 3.2
Classifier: Programming Language :: Python :: 3.3
Classifier: Programming Language :: Python :: 3.4
Requires-Python: >=3
